apispec_ui/__init__.py
apispec_ui/flask.py
apispec_ui/swagger-ui/VERSION
apispec_ui/swagger-ui/favicon-16x16.png
apispec_ui/swagger-ui/favicon-32x32.png
apispec_ui/swagger-ui/index.css
apispec_ui/swagger-ui/index.html
apispec_ui/swagger-ui/oauth2-redirect.html
apispec_ui/swagger-ui/swagger-ui-bundle.js
apispec_ui/swagger-ui/swagger-ui-bundle.js.map
apispec_ui/swagger-ui/swagger-ui-es-bundle-core.js
apispec_ui/swagger-ui/swagger-ui-es-bundle-core.js.map
apispec_ui/swagger-ui/swagger-ui-es-bundle.js
apispec_ui/swagger-ui/swagger-ui-es-bundle.js.map
apispec_ui/swagger-ui/swagger-ui-standalone-preset.js
apispec_ui/swagger-ui/swagger-ui-standalone-preset.js.map
apispec_ui/swagger-ui/swagger-ui.css
apispec_ui/swagger-ui/swagger-ui.css.map
apispec_ui/swagger-ui/swagger-ui.js
apispec_ui/swagger-ui/swagger-ui.js.map
apispec_ui/utils.py
apispec_ui-1.0.0.dist-info/LICENSE
apispec_ui-1.0.0.dist-info/METADATA
apispec_ui-1.0.0.dist-info/WHEEL
apispec_ui-1.0.0.dist-info/RECORD
