Metadata-Version: 2.1
Name: apispec-ui
Version: 1.0.0
Summary: Generate UI interactive API's from APISpec specifications.
Home-page: https://github.com/codectl/apispec-ui
License: MIT
Keywords: flaskful,swagger,openapi,oas,oas2,oas3,rest,api,web,flask,python,python3
Author: Renato Damas
Author-email: rena2damas@gmail.com
Requires-Python: >=3.8,<4.0
Classifier: Intended Audience :: Developers
Classifier: License :: OSI Approved :: MIT License
Classifier: Natural Language :: English
Classifier: Programming Language :: Python :: 3
Classifier: Programming Language :: Python :: 3.8
Classifier: Programming Language :: Python :: 3.9
Classifier: Programming Language :: Python :: 3.10
Classifier: Programming Language :: Python :: 3.11
Classifier: Programming Language :: Python :: 3
Classifier: Programming Language :: Python :: 3.10
Classifier: Programming Language :: Python :: 3.11
Classifier: Programming Language :: Python :: 3.8
Classifier: Programming Language :: Python :: 3.9
Requires-Dist: apispec[yaml] (>=6.3.0,<7.0.0)
Requires-Dist: environs (>=9.5.0,<10.0.0)
Requires-Dist: flask (>=2.2.3,<3.0.0)
Requires-Dist: gunicorn (>=20.1.0,<21.0.0)
Project-URL: Repository, https://github.com/codectl/apispec-ui
Project-URL: issues, https://github.com/codectl/apispec-ui/issues
